LICENSE
MANIFEST.in
README.md
setup.cfg
setup.py
flint/__init__.py
flint/executor.py
flint/version.py
flint_python_executor.egg-info/PKG-INFO
flint_python_executor.egg-info/SOURCES.txt
flint_python_executor.egg-info/dependency_links.txt
flint_python_executor.egg-info/requires.txt
flint_python_executor.egg-info/top_level.txt