Metadata-Version: 1.1
Name: flint-python-executor
Version: 0.3.4
Summary: flint python executor
Home-page: https://github.com/flintdev/flint-python-executor
Author: Gaoxin Dai
Author-email: daigx1990@gmail.com
License: Apache License 2.0
Platform: UNKNOWN
Classifier: Development Status :: 5 - Production/Stable
Classifier: Intended Audience :: Developers
Classifier: License :: OSI Approved :: Apache Software License
Classifier: Programming Language :: Python
Classifier: Programming Language :: Python :: 2
Classifier: Programming Language :: Python :: 3
